hatch_adder/__init__.py
hatch_adder/__main__.py
hatch_adder/cli/__init__.py
hatch_adder-0.0.2.dist-info/METADATA
hatch_adder-0.0.2.dist-info/WHEEL
hatch_adder-0.0.2.dist-info/entry_points.txt
hatch_adder-0.0.2.dist-info/licenses/LICENSE.txt
hatch_adder-0.0.2.dist-info/RECORD
