Metadata-Version: 2.4
Name: hatch-adder
Version: 0.0.2
Summary: Command to add/remove packages to pyproject.toml for hatch projects
Project-URL: Documentation, https://github.com/crast/hatch-adder#readme
Project-URL: Issues, https://github.com/crast/hatch-adder/issues
Project-URL: Source, https://github.com/crast/hatch-adder
Author-email: James Crasta <james@simplecodes.com>
License-Expression: MIT
License-File: LICENSE.txt
Classifier: Development Status :: 4 - Beta
Classifier: Programming Language :: Python
Classifier: Programming Language :: Python :: 3.10
Classifier: Programming Language :: Python :: 3.11
Classifier: Programming Language :: Python :: 3.12
Classifier: Programming Language :: Python :: Implementation :: CPython
Classifier: Programming Language :: Python :: Implementation :: PyPy
Requires-Python: >=3.10
Requires-Dist: uv
